thiscovery_dev_tools/__init__.py
thiscovery_dev_tools/deploy_to_aws.py
thiscovery_dev_tools/testing_tools.py
thiscovery_dev_tools/test_data/auth0_events.py
thiscovery_dev_tools-2021.2.dist-info/LICENSE
thiscovery_dev_tools-2021.2.dist-info/METADATA
thiscovery_dev_tools-2021.2.dist-info/WHEEL
thiscovery_dev_tools-2021.2.dist-info/top_level.txt
thiscovery_dev_tools-2021.2.dist-info/RECORD
