Metadata-Version: 2.1
Name: thiscovery-dev-tools
Version: 2021.2
Summary: Thiscovery development tools
Home-page: https://github.com/THIS-Institute/thiscovery-dev-tools
Author: Thiscovery team
Author-email: support@thiscovery.org
License: UNKNOWN
Platform: UNKNOWN
Classifier: Programming Language :: Python :: 3
Classifier: License :: OSI Approved :: GNU Affero General Public License v3
Classifier: Operating System :: OS Independent
Requires-Python: >=3.6
Requires-Dist: thiscovery-lib
Requires-Dist: pyyaml
